MANIFEST.in
README.rst
setup.cfg
setup.py
html5css3/__init__.py
html5css3/html.py
html5css3/main.py
html5css3/math.py
html5css3/postprocessors.py
html5css3/rst2html5-reveal.css
html5css3/rst2html5.css
html5css3/tests.py
html5css3/thirdparty/bootstrap.css
html5css3/thirdparty/jquery.js
html5css3/thirdparty/prettify.css
html5css3/thirdparty/prettify.js
html5css3/thirdparty/deckjs/.git
html5css3/thirdparty/deckjs/CHANGELOG.md
html5css3/thirdparty/deckjs/MIT-license.txt
html5css3/thirdparty/deckjs/Makefile
html5css3/thirdparty/deckjs/README.md
html5css3/thirdparty/deckjs/boilerplate.html
html5css3/thirdparty/deckjs/jquery.min.js
html5css3/thirdparty/deckjs/modernizr.custom.js
html5css3/thirdparty/deckjs/core/deck.core.css
html5css3/thirdparty/deckjs/core/deck.core.js
html5css3/thirdparty/deckjs/core/deck.core.scss
html5css3/thirdparty/deckjs/core/print.css
html5css3/thirdparty/deckjs/core/print.scss
html5css3/thirdparty/deckjs/extensions/goto/deck.goto.css
html5css3/thirdparty/deckjs/extensions/goto/deck.goto.html
html5css3/thirdparty/deckjs/extensions/goto/deck.goto.js
html5css3/thirdparty/deckjs/extensions/goto/deck.goto.scss
html5css3/thirdparty/deckjs/extensions/menu/deck.menu.css
html5css3/thirdparty/deckjs/extensions/menu/deck.menu.js
html5css3/thirdparty/deckjs/extensions/menu/deck.menu.scss
html5css3/thirdparty/deckjs/extensions/navigation/deck.navigation.css
html5css3/thirdparty/deckjs/extensions/navigation/deck.navigation.html
html5css3/thirdparty/deckjs/extensions/navigation/deck.navigation.js
html5css3/thirdparty/deckjs/extensions/navigation/deck.navigation.scss
html5css3/thirdparty/deckjs/extensions/scale/deck.scale.css
html5css3/thirdparty/deckjs/extensions/scale/deck.scale.js
html5css3/thirdparty/deckjs/extensions/scale/deck.scale.scss
html5css3/thirdparty/deckjs/extensions/status/deck.status.css
html5css3/thirdparty/deckjs/extensions/status/deck.status.html
html5css3/thirdparty/deckjs/extensions/status/deck.status.js
rst2html5_tools.egg-info/PKG-INFO
rst2html5_tools.egg-info/SOURCES.txt
rst2html5_tools.egg-info/dependency_links.txt
rst2html5_tools.egg-info/entry_points.txt
rst2html5_tools.egg-info/requires.txt
rst2html5_tools.egg-info/top_level.txt