Metadata-Version: 1.1
Name: rst2html5-tools
Version: 0.5.2
Summary: Transform reStructuredText documents to html5 + twitter's bootstrap css, deck.js or reveal.js
Home-page: https://github.com/marianoguerra/rst2html5
Author: Mariano Guerra
Author-email: luismarianoguerra@gmail.com
License: UNKNOWN
Platform: UNKNOWN
Classifier: Development Status :: 4 - Beta
Classifier: Environment :: Console
Classifier: Intended Audience :: Developers
Classifier: License :: OSI Approved :: MIT License
Classifier: Operating System :: OS Independent
Classifier: Programming Language :: Python
Classifier: Programming Language :: Python :: 2
Classifier: Programming Language :: Python :: 2.7
Classifier: Programming Language :: Python :: 3
Classifier: Programming Language :: Python :: 3.3
Classifier: Programming Language :: Python :: 3.4
Classifier: Topic :: Documentation
Classifier: Topic :: Software Development :: Libraries :: Python Modules
Classifier: Topic :: Text Processing
Classifier: Topic :: Text Processing :: Markup
Classifier: Topic :: Utilities
